readmemaker/__init__.py
readmemaker/__version__.py
readmemaker/py.typed
readmemaker-1.2.0.dist-info/LICENSE
readmemaker-1.2.0.dist-info/METADATA
readmemaker-1.2.0.dist-info/WHEEL
readmemaker-1.2.0.dist-info/top_level.txt
readmemaker-1.2.0.dist-info/RECORD
